LICENCE.txt
MANIFEST.in
README.md
setup.cfg
setup.py
openkts/__init__.py
openkts/__main__.py
openkts/common.py
openkts/sss.py
openkts/test_common.py
openkts/version.py
openkts.egg-info/PKG-INFO
openkts.egg-info/SOURCES.txt
openkts.egg-info/dependency_links.txt
openkts.egg-info/top_level.txt