Metadata-Version: 2.1
Name: openkts
Version: 1.1.4
Summary: Open Keyshare Threshold Scheme
Author: Anthony Kruger
Author-email: devadmin@impression.cloud
License: MIT
Keywords: keyshare
Classifier: Development Status :: 5 - Production/Stable
Classifier: Intended Audience :: Information Technology
Classifier: Operating System :: OS Independent
Classifier: License :: OSI Approved :: MIT License
Classifier: Programming Language :: Python :: 3
License-File: LICENCE.txt
